<?xml version="1.0" encoding="UTF-8" standalone="yes"?><ldapIdentityProviderConfig><oid>9371648</oid><version>1</version><name>QAAD MSAD</name><adminEnabled>true</adminEnabled><serializedProps>&lt;?xml version=&quot;1.0&quot; encoding=&quot;UTF-8&quot;?&gt; 
&lt;java version=&quot;1.5.0_11&quot; class=&quot;java.beans.XMLDecoder&quot;&gt; 
 &lt;object class=&quot;java.util.HashMap&quot;&gt; 
  &lt;void method=&quot;put&quot;&gt; 
   &lt;string&gt;ldapsearchbase&lt;/string&gt; 
   &lt;string&gt;ou=QA Test Users,dc=qaWin2003,dc=com&lt;/string&gt; 
  &lt;/void&gt; 
  &lt;void method=&quot;put&quot;&gt; 
   &lt;string&gt;originalTemplateName&lt;/string&gt; 
   &lt;string&gt;MicrosoftActiveDirectory&lt;/string&gt; 
  &lt;/void&gt; 
  &lt;void method=&quot;put&quot;&gt; 
   &lt;string&gt;usrmappings&lt;/string&gt; 
   &lt;object class=&quot;java.util.HashMap&quot;&gt; 
    &lt;void method=&quot;put&quot;&gt; 
     &lt;string&gt;user&lt;/string&gt; 
     &lt;object class=&quot;com.l7tech.identity.ldap.UserMappingConfig&quot;&gt; 
      &lt;void property=&quot;emailNameAttrName&quot;&gt; 
       &lt;string&gt;mail&lt;/string&gt; 
      &lt;/void&gt; 
      &lt;void property=&quot;firstNameAttrName&quot;&gt; 
       &lt;string&gt;givenName&lt;/string&gt; 
      &lt;/void&gt; 
      &lt;void property=&quot;lastNameAttrName&quot;&gt; 
       &lt;string&gt;sn&lt;/string&gt; 
      &lt;/void&gt; 
      &lt;void property=&quot;loginAttrName&quot;&gt; 
       &lt;string&gt;sAMAccountName&lt;/string&gt; 
      &lt;/void&gt; 
      &lt;void property=&quot;nameAttrName&quot;&gt; 
       &lt;string&gt;cn&lt;/string&gt; 
      &lt;/void&gt; 
      &lt;void property=&quot;objClass&quot;&gt; 
       &lt;string&gt;user&lt;/string&gt; 
      &lt;/void&gt; 
      &lt;void property=&quot;passwdAttrName&quot;&gt; 
       &lt;string&gt;userPassword&lt;/string&gt; 
      &lt;/void&gt; 
      &lt;void property=&quot;passwdType&quot;&gt; 
       &lt;object class=&quot;com.l7tech.identity.ldap.PasswdStrategy&quot;/&gt; 
      &lt;/void&gt; 
     &lt;/object&gt; 
    &lt;/void&gt; 
   &lt;/object&gt; 
  &lt;/void&gt; 
  &lt;void method=&quot;put&quot;&gt; 
   &lt;string&gt;grpmappings&lt;/string&gt; 
   &lt;object class=&quot;java.util.HashMap&quot;&gt; 
    &lt;void method=&quot;put&quot;&gt; 
     &lt;string&gt;group&lt;/string&gt; 
     &lt;object class=&quot;com.l7tech.identity.ldap.GroupMappingConfig&quot;&gt; 
      &lt;void property=&quot;memberAttrName&quot;&gt; 
       &lt;string&gt;member&lt;/string&gt; 
      &lt;/void&gt; 
      &lt;void property=&quot;memberStrategy&quot;&gt; 
       &lt;object class=&quot;com.l7tech.identity.ldap.MemberStrategy&quot;/&gt; 
      &lt;/void&gt; 
      &lt;void property=&quot;nameAttrName&quot;&gt; 
       &lt;string&gt;cn&lt;/string&gt; 
      &lt;/void&gt; 
      &lt;void property=&quot;objClass&quot;&gt; 
       &lt;string&gt;group&lt;/string&gt; 
      &lt;/void&gt; 
     &lt;/object&gt; 
    &lt;/void&gt; 
   &lt;/object&gt; 
  &lt;/void&gt; 
  &lt;void method=&quot;put&quot;&gt; 
   &lt;string&gt;ldapBindDN&lt;/string&gt; 
   &lt;string&gt;browse&lt;/string&gt; 
  &lt;/void&gt; 
  &lt;void method=&quot;put&quot;&gt; 
   &lt;string&gt;ldapBindPass&lt;/string&gt; 
   &lt;string&gt;password&lt;/string&gt; 
  &lt;/void&gt; 
  &lt;void method=&quot;put&quot;&gt; 
   &lt;string&gt;adminEnabled&lt;/string&gt; 
   &lt;boolean&gt;true&lt;/boolean&gt; 
  &lt;/void&gt; 
  &lt;void method=&quot;put&quot;&gt; 
   &lt;string&gt;ldapurl&lt;/string&gt; 
   &lt;array class=&quot;java.lang.String&quot; length=&quot;1&quot;&gt; 
    &lt;void index=&quot;0&quot;&gt; 
     &lt;string&gt;ldap://192.168.1.188:389&lt;/string&gt; 
    &lt;/void&gt; 
   &lt;/array&gt; 
  &lt;/void&gt; 
 &lt;/object&gt; 
&lt;/java&gt; 
</serializedProps><typeVal>2</typeVal><bindDN>browse</bindDN><bindPasswd>password</bindPasswd><groupMappings><memberAttrName>member</memberAttrName><memberStrategy><val>0</val></memberStrategy><nameAttrName>cn</nameAttrName><objClass>group</objClass></groupMappings><ldapUrl>ldap://192.168.1.188:389</ldapUrl><searchBase>ou=QA Test Users,dc=qaWin2003,dc=com</searchBase><templateName>MicrosoftActiveDirectory</templateName><userMappings><emailNameAttrName>mail</emailNameAttrName><firstNameAttrName>givenName</firstNameAttrName><lastNameAttrName>sn</lastNameAttrName><loginAttrName>sAMAccountName</loginAttrName><nameAttrName>cn</nameAttrName><objClass>user</objClass><passwdAttrName>userPassword</passwdAttrName><passwdType><val>0</val></passwdType></userMappings></ldapIdentityProviderConfig>