<?xml version="1.0" encoding="UTF-8" standalone="yes"?><jaxbPublishedService><PService><oid>3866627</oid><version>11</version><name>XpathEcho</name><disabled>false</disabled><httpMethodNames>POST</httpMethodNames><laxResolution>true</laxResolution><policy><oid>57311511</oid><version>0</version><name>Policy for service #3866627, XpathEcho</name><soap>true</soap><type>PRIVATE_SERVICE</type><versionActive>true</versionActive><versionOrdinal>-1</versionOrdinal><xml>&lt;?xml version=&quot;1.0&quot; encoding=&quot;UTF-8&quot;?&gt;
&lt;wsp:Policy xmlns:L7p=&quot;http://www.layer7tech.com/ws/policy&quot; xmlns:wsp=&quot;http://schemas.xmlsoap.org/ws/2002/12/policy&quot;&gt;
    &lt;wsp:All wsp:Usage=&quot;Required&quot;&gt;
        &lt;L7p:AuditAssertion&gt;
            &lt;L7p:SaveRequest booleanValue=&quot;true&quot;/&gt;
            &lt;L7p:SaveResponse booleanValue=&quot;true&quot;/&gt;
        &lt;/L7p:AuditAssertion&gt;
        &lt;wsse:SecurityToken xmlns:wsse=&quot;http://docs.oasis-open.org/wss/2004/01/oasis-200401-wss-wssecurity-secext-1.0.xsd&quot;&gt;
            &lt;wsse:TokenType&gt;urn:oasis:names:tc:SAML:2.0:assertion#Assertion&lt;/wsse:TokenType&gt;
            &lt;L7p:SamlParams&gt;
                &lt;L7p:AudienceRestriction stringValue=&quot;&quot;/&gt;
                &lt;L7p:SubjectConfirmations stringArrayValue=&quot;included&quot;&gt;
                    &lt;L7p:item stringValue=&quot;urn:oasis:names:tc:SAML:1.0:cm:sender-vouches&quot;/&gt;
                &lt;/L7p:SubjectConfirmations&gt;
                &lt;L7p:RequireSenderVouchesWithMessageSignature booleanValue=&quot;true&quot;/&gt;
                &lt;L7p:NameFormats stringArrayValue=&quot;included&quot;&gt;
                    &lt;L7p:item stringValue=&quot;urn:oasis:names:tc:SAML:1.1:nameid-format:unspecified&quot;/&gt;
                &lt;/L7p:NameFormats&gt;
                &lt;L7p:RequireHolderOfKeyWithMessageSignature booleanValue=&quot;true&quot;/&gt;
                &lt;L7p:CheckAssertionValidity booleanValue=&quot;false&quot;/&gt;
                &lt;L7p:AttributeStatement samlAttributeInfo=&quot;included&quot;&gt;
                    &lt;L7p:Attributes samlAttributeElementInfoArray=&quot;included&quot;&gt;
                        &lt;L7p:item samlAttributeElementInfo=&quot;included&quot;&gt;
                            &lt;L7p:Value stringValue=&quot;value_0&quot;/&gt;
                            &lt;L7p:Namespace stringValue=&quot;attributeNameSpace&quot;/&gt;
                            &lt;L7p:Name stringValue=&quot;attributeName&quot;/&gt;
                        &lt;/L7p:item&gt;
                    &lt;/L7p:Attributes&gt;
                &lt;/L7p:AttributeStatement&gt;
                &lt;L7p:NameQualifier stringValue=&quot;&quot;/&gt;
                &lt;L7p:Version boxedIntegerValue=&quot;0&quot;/&gt;
            &lt;/L7p:SamlParams&gt;
        &lt;/wsse:SecurityToken&gt;
        &lt;L7p:SpecificUser&gt;
            &lt;L7p:UserLogin stringValue=&quot;uid=joe,ou=people,ou=saml-demo,o=example.com&quot;/&gt;
            &lt;L7p:UserUid stringValue=&quot;3735553&quot;/&gt;
            &lt;L7p:IdentityProviderOid longValue=&quot;3702785&quot;/&gt;
            &lt;L7p:UserName stringValue=&quot;uid=joe,ou=people,ou=saml-demo,o=example.com&quot;/&gt;
        &lt;/L7p:SpecificUser&gt;
        &lt;wsp:MessagePredicate
            Dialect=&quot;http://www.w3.org/TR/1999/REC-xpath-19991116&quot;
            L7p:variablePrefix=&quot;foo&quot; wsp:Usage=&quot;wsp:Required&quot;
            xmlns:ds=&quot;http://www.w3.org/2000/09/xmldsig#&quot;
            xmlns:ns1=&quot;http://warehouse.acme.com/ws&quot;
            xmlns:saml=&quot;urn:oasis:names:tc:SAML:1.0:assertion&quot;
            xmlns:samlp=&quot;urn:oasis:names:tc:SAML:1.0:protocol&quot;
            xmlns:soapenv=&quot;http://schemas.xmlsoap.org/soap/envelope/&quot;
            xmlns:tns=&quot;http://xpathtest/ws&quot;
            xmlns:wsse=&quot;http://docs.oasis-open.org/wss/2004/01/oasis-200401-wss-wssecurity-secext-1.0.xsd&quot;
            xmlns:wsu=&quot;http://docs.oasis-open.org/wss/2004/01/oasis-200401-wss-wssecurity-utility-1.0.xsd&quot;
            xmlns:xsd=&quot;http://www.w3.org/2001/XMLSchema&quot; xmlns:xsi=&quot;http://www.w3.org/2001/XMLSchema-instance&quot;&gt;/soapenv:Envelope/soapenv:Header/wsse:Security/*[name()='Assertion']/*[name()='AttributeStatement']/*[name()='Subject']/*[name()='NameIdentifier']&lt;/wsp:MessagePredicate&gt;
        &lt;L7p:ComparisonAssertion&gt;
            &lt;L7p:Expression2 stringValue=&quot;uid=joe,ou=people,ou=saml-demo,o=example.com&quot;/&gt;
            &lt;L7p:Expression1 stringValue=&quot;${foo.result}&quot;/&gt;
        &lt;/L7p:ComparisonAssertion&gt;
        &lt;L7p:HttpRoutingAssertion&gt;
            &lt;L7p:ProtectedServiceUrl stringValue=&quot;http://hugh/ACMEWarehouseWS/Service1.asmx&quot;/&gt;
        &lt;/L7p:HttpRoutingAssertion&gt;
    &lt;/wsp:All&gt;
&lt;/wsp:Policy&gt;
</xml></policy><routingUri>/xml/xpathpolicyvariableSAMLattribute22</routingUri><soap>true</soap><wsdlUrl>http://hugh/XPathTestService/Service.asmx?wsdl</wsdlUrl><wsdlXml>&lt;?xml version=&quot;1.0&quot; encoding=&quot;utf-8&quot;?&gt;
&lt;wsdl:definitions xmlns:soap=&quot;http://schemas.xmlsoap.org/wsdl/soap/&quot; xmlns:tm=&quot;http://microsoft.com/wsdl/mime/textMatching/&quot; xmlns:soapenc=&quot;http://schemas.xmlsoap.org/soap/encoding/&quot; xmlns:mime=&quot;http://schemas.xmlsoap.org/wsdl/mime/&quot; xmlns:tns=&quot;http://xpathtest/ws&quot; xmlns:s=&quot;http://www.w3.org/2001/XMLSchema&quot; xmlns:soap12=&quot;http://schemas.xmlsoap.org/wsdl/soap12/&quot; xmlns:http=&quot;http://schemas.xmlsoap.org/wsdl/http/&quot; targetNamespace=&quot;http://xpathtest/ws&quot; xmlns:wsdl=&quot;http://schemas.xmlsoap.org/wsdl/&quot;&gt;
  &lt;wsdl:types&gt;
    &lt;s:schema elementFormDefault=&quot;qualified&quot; targetNamespace=&quot;http://xpathtest/ws&quot;&gt;
      &lt;s:element name=&quot;XpathEchoAll&quot;&gt;
        &lt;s:complexType&gt;
          &lt;s:sequence&gt;
            &lt;s:element minOccurs=&quot;0&quot; maxOccurs=&quot;1&quot; name=&quot;name1&quot; type=&quot;s:string&quot; /&gt;
            &lt;s:element minOccurs=&quot;0&quot; maxOccurs=&quot;1&quot; name=&quot;name2&quot; type=&quot;s:string&quot; /&gt;
            &lt;s:element minOccurs=&quot;1&quot; maxOccurs=&quot;1&quot; name=&quot;price1&quot; type=&quot;s:double&quot; /&gt;
            &lt;s:element minOccurs=&quot;1&quot; maxOccurs=&quot;1&quot; name=&quot;price2&quot; type=&quot;s:double&quot; /&gt;
            &lt;s:element minOccurs=&quot;1&quot; maxOccurs=&quot;1&quot; name=&quot;inStore1&quot; type=&quot;s:boolean&quot; /&gt;
            &lt;s:element minOccurs=&quot;1&quot; maxOccurs=&quot;1&quot; name=&quot;isImported2&quot; type=&quot;s:boolean&quot; /&gt;
          &lt;/s:sequence&gt;
        &lt;/s:complexType&gt;
      &lt;/s:element&gt;
      &lt;s:element name=&quot;XpathEchoAllResponse&quot;&gt;
        &lt;s:complexType&gt;
          &lt;s:sequence&gt;
            &lt;s:element minOccurs=&quot;0&quot; maxOccurs=&quot;1&quot; name=&quot;XpathEchoAllResult&quot; type=&quot;tns:car&quot; /&gt;
          &lt;/s:sequence&gt;
        &lt;/s:complexType&gt;
      &lt;/s:element&gt;
      &lt;s:complexType name=&quot;car&quot;&gt;
        &lt;s:sequence&gt;
          &lt;s:element minOccurs=&quot;0&quot; maxOccurs=&quot;1&quot; name=&quot;name1&quot; type=&quot;s:string&quot; /&gt;
          &lt;s:element minOccurs=&quot;0&quot; maxOccurs=&quot;1&quot; name=&quot;name2&quot; type=&quot;s:string&quot; /&gt;
          &lt;s:element minOccurs=&quot;1&quot; maxOccurs=&quot;1&quot; name=&quot;price1&quot; type=&quot;s:double&quot; /&gt;
          &lt;s:element minOccurs=&quot;1&quot; maxOccurs=&quot;1&quot; name=&quot;price2&quot; type=&quot;s:double&quot; /&gt;
          &lt;s:element minOccurs=&quot;1&quot; maxOccurs=&quot;1&quot; name=&quot;inStore1&quot; type=&quot;s:boolean&quot; /&gt;
          &lt;s:element minOccurs=&quot;1&quot; maxOccurs=&quot;1&quot; name=&quot;isImported2&quot; type=&quot;s:boolean&quot; /&gt;
        &lt;/s:sequence&gt;
      &lt;/s:complexType&gt;
    &lt;/s:schema&gt;
  &lt;/wsdl:types&gt;
  &lt;wsdl:message name=&quot;XpathEchoAllSoapIn&quot;&gt;
    &lt;wsdl:part name=&quot;parameters&quot; element=&quot;tns:XpathEchoAll&quot; /&gt;
  &lt;/wsdl:message&gt;
  &lt;wsdl:message name=&quot;XpathEchoAllSoapOut&quot;&gt;
    &lt;wsdl:part name=&quot;parameters&quot; element=&quot;tns:XpathEchoAllResponse&quot; /&gt;
  &lt;/wsdl:message&gt;
  &lt;wsdl:portType name=&quot;XpathEchoSoap&quot;&gt;
    &lt;wsdl:operation name=&quot;XpathEchoAll&quot;&gt;
      &lt;wsdl:input message=&quot;tns:XpathEchoAllSoapIn&quot; /&gt;
      &lt;wsdl:output message=&quot;tns:XpathEchoAllSoapOut&quot; /&gt;
    &lt;/wsdl:operation&gt;
  &lt;/wsdl:portType&gt;
  &lt;wsdl:binding name=&quot;XpathEchoSoap&quot; type=&quot;tns:XpathEchoSoap&quot;&gt;
    &lt;soap:binding transport=&quot;http://schemas.xmlsoap.org/soap/http&quot; /&gt;
    &lt;wsdl:operation name=&quot;XpathEchoAll&quot;&gt;
      &lt;soap:operation soapAction=&quot;http://xpathtest/ws/XpathEchoAll&quot; style=&quot;document&quot; /&gt;
      &lt;wsdl:input&gt;
        &lt;soap:body use=&quot;literal&quot; /&gt;
      &lt;/wsdl:input&gt;
      &lt;wsdl:output&gt;
        &lt;soap:body use=&quot;literal&quot; /&gt;
      &lt;/wsdl:output&gt;
    &lt;/wsdl:operation&gt;
  &lt;/wsdl:binding&gt;
  &lt;wsdl:binding name=&quot;XpathEchoSoap12&quot; type=&quot;tns:XpathEchoSoap&quot;&gt;
    &lt;soap12:binding transport=&quot;http://schemas.xmlsoap.org/soap/http&quot; /&gt;
    &lt;wsdl:operation name=&quot;XpathEchoAll&quot;&gt;
      &lt;soap12:operation soapAction=&quot;http://xpathtest/ws/XpathEchoAll&quot; style=&quot;document&quot; /&gt;
      &lt;wsdl:input&gt;
        &lt;soap12:body use=&quot;literal&quot; /&gt;
      &lt;/wsdl:input&gt;
      &lt;wsdl:output&gt;
        &lt;soap12:body use=&quot;literal&quot; /&gt;
      &lt;/wsdl:output&gt;
    &lt;/wsdl:operation&gt;
  &lt;/wsdl:binding&gt;
  &lt;wsdl:service name=&quot;XpathEcho&quot;&gt;
    &lt;wsdl:port name=&quot;XpathEchoSoap&quot; binding=&quot;tns:XpathEchoSoap&quot;&gt;
      &lt;soap:address location=&quot;http://hugh/XPathTestService/Service.asmx&quot; /&gt;
    &lt;/wsdl:port&gt;
    &lt;wsdl:port name=&quot;XpathEchoSoap12&quot; binding=&quot;tns:XpathEchoSoap12&quot;&gt;
      &lt;soap12:address location=&quot;http://hugh/XPathTestService/Service.asmx&quot; /&gt;
    &lt;/wsdl:port&gt;
  &lt;/wsdl:service&gt;
&lt;/wsdl:definitions&gt;</wsdlXml></PService></jaxbPublishedService>