<?xml version="1.0" encoding="UTF-8"?>
<optionSet id="status">
    <description>
----------------------------------------------------------------------
SecureSpan Gateway Status
----------------------------------------------------------------------</description>

    <!--
      Options for node status display
    -->
    <option id="status" type="TEXT" order="100" name="Node Status">
        <configName>status</configName>
        <description>Node Status</description>
        <prompt>Node Status.</prompt>
    </option>

</optionSet>
